[
    {
        "day": 1,
        "Sahri": "05:25",
        "Sunrise": "05:31",
        "Zohar": "12:16",
        "Asr": "16:05",
        "Maghrib": "17:45",
        "Isha": "19:00"
    },
    {
        "day": 2,
        "Sahri": "05:26",
        "Sunrise": "05:32",
        "Zohar": "12:16",
        "Asr": "16:05",
        "Maghrib": "17:45",
        "Isha": "19:00"
    },
    {
        "day": 3,
        "Sahri": "05:27",
        "Sunrise": "05:33",
        "Zohar": "12:16",
        "Asr": "16:05",
        "Maghrib": "17:45",
        "Isha": "19:00"
    },
    {
        "day": 4,
        "Sahri": "05:27",
        "Sunrise": "05:33",
        "Zohar": "12:17",
        "Asr": "16:05",
        "Maghrib": "17:45",
        "Isha": "19:00"
    },
    {
        "day": 5,
        "Sahri": "05:28",
        "Sunrise": "05:34",
        "Zohar": "12:17",
        "Asr": "16:05",
        "Maghrib": "17:45",
        "Isha": "19:01"
    },
    {
        "day": 6,
        "Sahri": "05:28",
        "Sunrise": "05:34",
        "Zohar": "12:18",
        "Asr": "16:05",
        "Maghrib": "17:45",
        "Isha": "19:01"
    },
    {
        "day": 7,
        "Sahri": "05:29",
        "Sunrise": "05:35",
        "Zohar": "12:18",
        "Asr": "16:06",
        "Maghrib": "17:45",
        "Isha": "19:01"
    },
    {
        "day": 8,
        "Sahri": "05:29",
        "Sunrise": "05:35",
        "Zohar": "12:19",
        "Asr": "16:06",
        "Maghrib": "17:45",
        "Isha": "19:01"
    },
    {
        "day": 9,
        "Sahri": "05:30",
        "Sunrise": "05:36",
        "Zohar": "12:19",
        "Asr": "16:06",
        "Maghrib": "17:46",
        "Isha": "19:02"
    },
    {
        "day": 10,
        "Sahri": "05:30",
        "Sunrise": "05:36",
        "Zohar": "12:20",
        "Asr": "16:06",
        "Maghrib": "17:46",
        "Isha": "19:02"
    },
    {
        "day": 11,
        "Sahri": "05:31",
        "Sunrise": "05:37",
        "Zohar": "12:20",
        "Asr": "16:07",
        "Maghrib": "17:46",
        "Isha": "19:02"
    },
    {
        "day": 12,
        "Sahri": "05:31",
        "Sunrise": "05:37",
        "Zohar": "12:21",
        "Asr": "16:07",
        "Maghrib": "17:46",
        "Isha": "19:02"
    },
    {
        "day": 13,
        "Sahri": "05:32",
        "Sunrise": "05:38",
        "Zohar": "12:21",
        "Asr": "16:07",
        "Maghrib": "17:47",
        "Isha": "19:03"
    },
    {
        "day": 14,
        "Sahri": "05:33",
        "Sunrise": "05:39",
        "Zohar": "12:22",
        "Asr": "16:07",
        "Maghrib": "17:47",
        "Isha": "19:03"
    },
    {
        "day": 15,
        "Sahri": "05:34",
        "Sunrise": "05:40",
        "Zohar": "12:22",
        "Asr": "16:08",
        "Maghrib": "17:48",
        "Isha": "19:04"
    },
    {
        "day": 16,
        "Sahri": "05:34",
        "Sunrise": "05:40",
        "Zohar": "12:23",
        "Asr": "16:08",
        "Maghrib": "17:48",
        "Isha": "19:04"
    },
    {
        "day": 17,
        "Sahri": "05:35",
        "Sunrise": "05:41",
        "Zohar": "12:23",
        "Asr": "16:09",
        "Maghrib": "17:48",
        "Isha": "19:05"
    },
    {
        "day": 18,
        "Sahri": "05:35",
        "Sunrise": "05:41",
        "Zohar": "12:24",
        "Asr": "16:09",
        "Maghrib": "17:48",
        "Isha": "19:05"
    },
    {
        "day": 19,
        "Sahri": "05:36",
        "Sunrise": "05:42",
        "Zohar": "12:24",
        "Asr": "16:09",
        "Maghrib": "17:49",
        "Isha": "19:06"
    },
    {
        "day": 20,
        "Sahri": "05:36",
        "Sunrise": "05:42",
        "Zohar": "12:25",
        "Asr": "16:09",
        "Maghrib": "17:49",
        "Isha": "19:06"
    },
    {
        "day": 21,
        "Sahri": "05:37",
        "Sunrise": "05:43",
        "Zohar": "12:25",
        "Asr": "16:10",
        "Maghrib": "17:50",
        "Isha": "19:07"
    },
    {
        "day": 22,
        "Sahri": "05:37",
        "Sunrise": "05:43",
        "Zohar": "12:26",
        "Asr": "16:10",
        "Maghrib": "17:50",
        "Isha": "19:07"
    },
    {
        "day": 23,
        "Sahri": "05:38",
        "Sunrise": "05:44",
        "Zohar": "12:26",
        "Asr": "16:11",
        "Maghrib": "17:51",
        "Isha": "19:08"
    },
    {
        "day": 24,
        "Sahri": "05:38",
        "Sunrise": "05:44",
        "Zohar": "12:27",
        "Asr": "16:11",
        "Maghrib": "17:51",
        "Isha": "19:08"
    },
    {
        "day": 25,
        "Sahri": "05:39",
        "Sunrise": "05:45",
        "Zohar": "12:27",
        "Asr": "16:12",
        "Maghrib": "17:52",
        "Isha": "19:09"
    },
    {
        "day": 26,
        "Sahri": "05:39",
        "Sunrise": "05:46",
        "Zohar": "12:27",
        "Asr": "16:13",
        "Maghrib": "17:52",
        "Isha": "19:09"
    },
    {
        "day": 27,
        "Sahri": "05:40",
        "Sunrise": "05:46",
        "Zohar": "12:28",
        "Asr": "16:14",
        "Maghrib": "17:53",
        "Isha": "19:10"
    },
    {
        "day": 28,
        "Sahri": "05:40",
        "Sunrise": "05:46",
        "Zohar": "12:28",
        "Asr": "16:14",
        "Maghrib": "17:53",
        "Isha": "19:10"
    },
    {
        "day": 29,
        "Sahri": "05:40",
        "Sunrise": "05:46",
        "Zohar": "12:29",
        "Asr": "16:15",
        "Maghrib": "17:54",
        "Isha": "19:11"
    },
    {
        "day": 30,
        "Sahri": "05:40",
        "Sunrise": "05:47",
        "Zohar": "12:29",
        "Asr": "16:15",
        "Maghrib": "17:55",
        "Isha": "19:11"
    },
    {
        "day": 31,
        "Sahri": "05:41",
        "Sunrise": "05:47",
        "Zohar": "12:30",
        "Asr": "16:16",
        "Maghrib": "17:56",
        "Isha": "19:12"
    }
]